setup.py
sg_socket_constants.py
sg_socket_constants.egg-info/PKG-INFO
sg_socket_constants.egg-info/SOURCES.txt
sg_socket_constants.egg-info/dependency_links.txt
sg_socket_constants.egg-info/top_level.txt