Metadata-Version: 1.0
Name: sg-socket-constants
Version: 1.6.1
Summary: Constants variables for socket
Home-page: https://github.com/realglobe-Inc/sg-socket-constants#readme
Author: Taka Okunishi
Author-email: okunishitaka.com@gmail.com
License: Apache-2.0
Platform: UNKNOWN
